app/__init__.py
balli_yourip-0.2.0.dist-info/METADATA
balli_yourip-0.2.0.dist-info/WHEEL
balli_yourip-0.2.0.dist-info/entry_points.txt
balli_yourip-0.2.0.dist-info/RECORD
