Metadata-Version: 2.4
Name: balli_yourip
Version: 0.2.0
Summary: Add your description here
Author-email: BalliAsghar <ballihacker@outlook.com>
Requires-Python: >=3.13
Requires-Dist: click>=8.1.8
Requires-Dist: requests>=2.32.3
